[
  {
    "img-src": "html5-room/images/picture3.jpeg",
    "img-alt": "animation-circle",
    "img-title": "animation-circle",
    "name": "animation-circle",
    "aref": "animation-circle/index.html"
  },
  {
    "img-src": "html5-room/images/picture3.jpeg",
    "img-alt": "animation-city",
    "img-title": "animation-city",
    "name": "animation-city",
    "aref": "animation-city/index.html"
  },
  {
    "img-src": "html5-room/images/picture1.jpeg",
    "img-alt": "WebSite",
    "img-title": "WebSite",
    "name": "create-lab",
    "aref": "create-lab/index.html"
  },
  {
    "img-src": "html5-room/images/picture1.jpeg",
    "img-alt": "WebSite",
    "img-title": "WebSite",
    "name": "css3-shapes",
    "aref": "css3-shapes/index.html"
  },
  {
    "img-src": "html5-room/images/picture1.jpeg",
    "img-alt": "description",
    "img-title": "description",
    "name": "cyber-city",
    "aref": "cyber-city/index.html"
  },
  {
    "img-src": "html5-room/images/picture1.jpeg",
    "img-alt": "WebSite",
    "img-title": "WebSite",
    "name": "eight",
    "aref": "eight/index.html"
  },
  {
    "img-src": "html5-room/images/picture1.jpeg",
    "img-alt": "github-avatar",
    "img-title": "github-avatar",
    "name": "github-avatar",
    "aref": "github-avatar/index.html"
  },

  {
    "img-src": "html5-room/images/picture2.jpeg",
    "img-alt": "description",
    "img-title": "description",
    "name": "hive-board",
    "aref": "hive-board/index.html"
  },
  {
    "img-src": "html5-room/images/picture3.jpeg",
    "img-alt": "animation-city",
    "img-title": "animation-city",
    "name": "animation-city",
    "aref": "animation-city/index.html"
  },
  {
    "img-src": "html5-room/images/picture3.jpeg",
    "img-alt": "temporal-vendetta",
    "img-title": "temporal-vendetta",
    "name": "temporal-vendetta",
    "aref": "temporal-vendetta/index.html"
  },
  {
    "img-src": "html5-room/images/picture3.jpeg",
    "img-alt": "layouts",
    "img-title": "layouts",
    "name": "layouts",
    "aref": "layouts/index.html"
  },
  {
    "img-src": "html5-room/images/picture1.jpeg",
    "img-alt": "nz-map",
    "img-title": "nz-map",
    "name": "nz-map",
    "aref": "nz-map/index.html"
  },
  {
    "img-src": "html5-room/images/picture2.jpeg",
    "img-alt": "splash",
    "img-title": "splash",
    "name": "splash",
    "aref": "splash/index.html"
  },
  {
    "img-src": "html5-room/images/picture3.jpeg",
    "img-alt": "80s",
    "img-title": "80s",
    "name": "80s",
    "aref": "80s/index.html"
  }
]
